[
  {
    "id": 1,
    "category": "functional",
    "description": "reward system - Four-dimensional reward calculation",
    "steps": [
      "createRewardSignalkind",
      "Realize four-dimensional reward signals（objective indicators、user behavior、explicit feedback、behavior pattern）",
      "Implement dynamic weight adjustment",
      "accomplishRewardCalculatorCompute engine",
      "Write unit tests"
    ],
    "passes": true
  },
  {
    "id": 2,
    "category": "functional",
    "description": "interactive environment - state/action space definition",
    "steps": [
      "define state space（task_type, tech_stack, user_moodwait）",
      "Define action space（agent_selection, automation_levelwait）",
      "accomplishreset()method",
      "accomplishstep()method",
      "Write unit tests"
    ],
    "passes": true
  },
  {
    "id": 3,
    "category": "functional",
    "description": "RLagent - Actor-Criticaccomplish",
    "steps": [
      "accomplishPolicyNetwork（policy network）",
      "accomplishValueNetwork（value network）",
      "accomplishAlignmentAgent（Actor-Criticagent）",
      "accomplishselect_action()method",
      "accomplishupdate_policy()method",
      "Write unit tests"
    ],
    "passes": true
  },
  {
    "id": 4,
    "category": "functional",
    "description": "Learner reconstruction - Moving from statistical learningRL",
    "steps": [
      "createRLLearnerkind",
      "accomplishlearn_from_task()online learning",
      "accomplishsave_model()Save model",
      "keep withPreferenceLearnerbackwards compatible",
      "Write unit tests"
    ],
    "passes": true
  },
  {
    "id": 5,
    "category": "functional",
    "description": "Integrated engine extension - new interface",
    "steps": [
      "accomplishon_task_start()interface",
      "accomplishon_task_complete()interface",
      "integratedRLLearner",
      "Write integration tests"
    ],
    "passes": true
  },
  {
    "id": 6,
    "category": "optimization",
    "description": "neural network model - OptionalPyTorchaccomplish",
    "steps": [
      "DetectionPyTorchAvailability",
      "accomplishPyTorchversion policy network",
      "accomplishPyTorchversion value network",
      "Implement intelligent downgrade（nonePyTorchUsed whenNumPy）"
    ],
    "passes": true
  },
  {
    "id": 7,
    "category": "optimization",
    "description": "Experience replay - Improve sample efficiency",
    "steps": [
      "createExperienceReplaykind",
      "Implement experience storage",
      "Implement priority sampling",
      "Implement batch sampling"
    ],
    "passes": true
  },
  {
    "id": 8,
    "category": "optimization",
    "description": "trainer - Complete training cycle",
    "steps": [
      "createRLTrainerkind",
      "Achieve moreepisodetraining loop",
      "Implement checkpoint saving/load",
      "Implement training statistics and visualization"
    ],
    "passes": true
  },
  {
    "id": 9,
    "category": "advanced",
    "description": "Distributed training support",
    "steps": [
      "integratedRedis + Celery",
      "Implement multi-project parallel training"
    ],
    "passes": false
  },
  {
    "id": 10,
    "category": "advanced",
    "description": "Monitoring panel - TensorBoardintegrated",
    "steps": [
      "integratedTensorBoard",
      "Visualize the reward curve",
      "Implement training progress monitoring"
    ],
    "passes": false
  }
]
